openlibrary_api/__init__.py
openlibrary_api/errors.py
openlibrary_api/models.py
openlibrary_api/ol_api.py
openlibrary_api-0.0.8.dist-info/METADATA
openlibrary_api-0.0.8.dist-info/WHEEL
openlibrary_api-0.0.8.dist-info/licenses/LICENSE
openlibrary_api-0.0.8.dist-info/RECORD
